README.md
pyproject.toml
setup.py
streamfieldindex/__init__.py
streamfieldindex/indexer.py
streamfieldindex/iterator.py
streamfieldindex/modeladmin.py
streamfieldindex/models.py
streamfieldindex/wagtail_hooks.py
streamfieldindex/management/__init__.py
streamfieldindex/management/commands/__init__.py
streamfieldindex/management/commands/streamfieldindex.py
streamfieldindex/migrations/0001_initial.py
streamfieldindex/migrations/__init__.py
tests/__init__.py
tests/conftest.py
tests/settings.py
tests/test_get_bound_block.py
tests/test_indexer.py
tests/testapp/__init__.py
tests/testapp/blocks.py
tests/testapp/models.py
tests/testapp/urls.py
tests/testapp/wagtail_hooks.py
tests/testapp/migrations/0001_initial.py
tests/testapp/migrations/__init__.py
wagtail_streamfield_index.egg-info/PKG-INFO
wagtail_streamfield_index.egg-info/SOURCES.txt
wagtail_streamfield_index.egg-info/dependency_links.txt
wagtail_streamfield_index.egg-info/requires.txt
wagtail_streamfield_index.egg-info/top_level.txt