Metadata-Version: 2.1
Name: wagtail-streamfield-index
Version: 0.0.2
Summary: Indexing for Wagtail streamfields
Home-page: https://github.com/nhsuk/wagtail-streamfield-index
Author: Mike Monteith
Author-email: <mike.monteith@nhs.net>
License: UNKNOWN
Platform: UNKNOWN
Provides-Extra: testing
Provides-Extra: linting
